gnnnas/__init__.py
gnnnas/data.py
gnnnas/models.py
gnnnas/util.py
gnnnas-0.0.2.dist-info/LICENSE
gnnnas-0.0.2.dist-info/METADATA
gnnnas-0.0.2.dist-info/WHEEL
gnnnas-0.0.2.dist-info/RECORD
