Metadata-Version: 2.1
Name: gnnnas
Version: 0.0.2
Summary: Library to help write symbolic programs to generate expressive message passing neural networks.
License: MIT
Author: Your Name
Author-email: you@example.com
Requires-Python: >=3.10,<3.13
Classifier: License :: OSI Approved :: MIT License
Classifier: Programming Language :: Python :: 3
Classifier: Programming Language :: Python :: 3.10
Classifier: Programming Language :: Python :: 3.11
Requires-Dist: numpy (>=1.26.1,<2.0.0)
Requires-Dist: pdoc3 (>=0.10.0,<0.11.0)
Requires-Dist: pytest (>=7.4.2,<8.0.0)
Requires-Dist: scikit-learn (>=1.3.1,<2.0.0)
Requires-Dist: torch (==1.12.1)
Requires-Dist: torch-geometric (>=2.4.0,<3.0.0)
